sophi_app_internal/__init__.py
sophi_app_internal/main.py
sophi_app_internal/Downloaders/__init__.py
sophi_app_internal/Downloaders/GoogleDrive/GoogleDriveDownloader.py
sophi_app_internal/Downloaders/GoogleDrive/__init__.py
sophi_app_internal/Downloaders/GoogleDrive/ToPDF/GoogleDocs.py
sophi_app_internal/Downloaders/GoogleDrive/ToPDF/GoogleDrivePDF.py
sophi_app_internal/Downloaders/GoogleDrive/ToPDF/__init__.py
sophi_app_internal/Downloaders/GoogleDrive/ToXLSX/GoogleSpreadsheet.py
sophi_app_internal/Downloaders/GoogleDrive/ToXLSX/__init__.py
sophi_app_internal/Intergrations/__init__.py
sophi_app_internal/Intergrations/Auth0/__init__.py
sophi_app_internal/Intergrations/Auth0/management_api.py
sophi_app_internal/Intergrations/Auth0/token_validation.py
sophi_app_internal/Intergrations/Github/__init__.py
sophi_app_internal/Intergrations/Github/githubintergration.py
sophi_app_internal/Intergrations/Google/__init__.py
sophi_app_internal/Intergrations/Google/google.py
sophi_app_internal/Intergrations/Microsoft/__init__.py
sophi_app_internal/Intergrations/Microsoft/azure.py
sophi_app_internal/Intergrations/Microsoft/cosmos_client.py
sophi_app_internal/Intergrations/Microsoft/cosmos_client_initialization.py
sophi_app_internal/Intergrations/Slack/__init__.py
sophi_app_internal/Intergrations/Slack/slack.py
sophi_app_internal/Security/__init__.py
sophi_app_internal/Security/base_64_private_key.py
sophi_app_internal/Security/token_crypto.py
sophi_app_internal-0.1.23.dist-info/METADATA
sophi_app_internal-0.1.23.dist-info/WHEEL
sophi_app_internal-0.1.23.dist-info/top_level.txt
sophi_app_internal-0.1.23.dist-info/RECORD
