Metadata-Version: 2.1
Name: sophi-app-internal
Version: 0.1.23
Requires-Dist: requests
Requires-Dist: pyjwt
Requires-Dist: cryptography
Requires-Dist: python-jose
Requires-Dist: pydantic
Requires-Dist: azure-cosmos
Requires-Dist: python-dotenv
Requires-Dist: auth0-python
Requires-Dist: google-api-python-client
Requires-Dist: google-auth-oauthlib
Requires-Dist: azure-storage-blob
Requires-Dist: slack-sdk
Requires-Dist: PyGithub
